fhswiftui/__init__.py
fhswiftui/_modidx.py
fhswiftui/core.py
fhswiftui-0.0.5.dist-info/licenses/LICENSE
fhswiftui-0.0.5.dist-info/METADATA
fhswiftui-0.0.5.dist-info/WHEEL
fhswiftui-0.0.5.dist-info/entry_points.txt
fhswiftui-0.0.5.dist-info/top_level.txt
fhswiftui-0.0.5.dist-info/RECORD
