Metadata-Version: 2.4
Name: fhswiftui
Version: 0.0.5
Summary: SwiftUI inspired wrapper for FastHTML
Home-page: https://github.com/thechandru/fhswiftui
Author: Chandru Subramanian
Author-email: pypi@chandru.blog
License: Apache Software License 2.0
Keywords: fasthtml basecoat swiftui python
Classifier: Development Status :: 4 - Beta
Classifier: Intended Audience :: Developers
Classifier: Natural Language :: English
Classifier: Programming Language :: Python :: 3.9
Classifier: Programming Language :: Python :: 3.10
Classifier: Programming Language :: Python :: 3.11
Classifier: Programming Language :: Python :: 3.12
Classifier: License :: OSI Approved :: Apache Software License
Requires-Python: >=3.9
License-File: LICENSE
Requires-Dist: fastcore
Requires-Dist: python-fasthtml
Provides-Extra: dev
Dynamic: author
Dynamic: author-email
Dynamic: classifier
Dynamic: description
Dynamic: description-content-type
Dynamic: home-page
Dynamic: keywords
Dynamic: license
Dynamic: license-file
Dynamic: provides-extra
Dynamic: requires-dist
Dynamic: requires-python
Dynamic: summary
